elusion/__init__.py
elusion/zenopay/__init__.py
elusion/zenopay/client.py
elusion/zenopay/config.py
elusion/zenopay/exceptions.py
elusion/zenopay/py.typed
elusion/zenopay/http/__init__.py
elusion/zenopay/http/client.py
elusion/zenopay/models/__init__.py
elusion/zenopay/models/checkout.py
elusion/zenopay/models/common.py
elusion/zenopay/models/disbursement.py
elusion/zenopay/models/order.py
elusion/zenopay/models/payment.py
elusion/zenopay/models/utility_payments.py
elusion/zenopay/models/webhook.py
elusion/zenopay/services/__init__.py
elusion/zenopay/services/base.py
elusion/zenopay/services/checkout.py
elusion/zenopay/services/disbursements.py
elusion/zenopay/services/orders.py
elusion/zenopay/services/utility_payments.py
elusion/zenopay/services/webhooks.py
elusion/zenopay/utils/__init__.py
elusion/zenopay/utils/helpers.py
zenopay_sdk-0.4.1.dist-info/METADATA
zenopay_sdk-0.4.1.dist-info/WHEEL
zenopay_sdk-0.4.1.dist-info/licenses/LICENSE
zenopay_sdk-0.4.1.dist-info/RECORD
