Metadata-Version: 2.4
Name: zenopay-sdk
Version: 0.4.1
Summary: A modern Python SDK for the ZenoPay payment API
Project-URL: Homepage, https://github.com/elusionhub/zenopay-python-sdk
Project-URL: Documentation, https://github.com/elusionhub/zenopay-python-sdk#readme
Project-URL: Repository, https://github.com/elusionhub/zenopay-python-sdk.git
Project-URL: Issues, https://github.com/elusionhub/zenopay-python-sdk/issues
Project-URL: Changelog, https://github.com/elusionhub/zenopay-python-sdk/blob/main/CHANGELOG.md
Author-email: Elution Hub <elusion.lab@gmail.com>
Maintainer-email: Elution Hub <elusion.lab@gmail.com>
License-Expression: MIT
License-File: LICENSE
Keywords: africa,api,mobile-money,payments,payments-gateway,sdk,tanzania,ussd,zenopay
Classifier: Development Status :: 4 - Beta
Classifier: Intended Audience :: Developers
Classifier: License :: OSI Approved :: MIT License
Classifier: Operating System :: OS Independent
Classifier: Programming Language :: Python :: 3
Classifier: Programming Language :: Python :: 3.8
Classifier: Programming Language :: Python :: 3.9
Classifier: Programming Language :: Python :: 3.10
Classifier: Programming Language :: Python :: 3.11
Classifier: Programming Language :: Python :: 3.12
Classifier: Topic :: Office/Business :: Financial :: Point-Of-Sale
Classifier: Topic :: Software Development :: Libraries :: Python Modules
Classifier: Typing :: Typed
Requires-Python: >=3.8
Requires-Dist: httpx>=0.28.1
Requires-Dist: pydantic>=2.0.0
Requires-Dist: python-dotenv>=1.1.1
Requires-Dist: typing-extensions>=4.14.0; python_version < '3.11'
Provides-Extra: dev
Requires-Dist: black>=25.1.0; extra == 'dev'
Requires-Dist: flake8>=6.0.0; extra == 'dev'
Requires-Dist: ginx>=0.1.6; extra == 'dev'
Requires-Dist: mypy>=1.0.0; extra == 'dev'
Requires-Dist: pre-commit>=3.0.0; extra == 'dev'
Requires-Dist: pytest-asyncio>=0.21.0; extra == 'dev'
Requires-Dist: pytest-cov>=6.2.1; extra == 'dev'
Requires-Dist: pytest-mock>=3.10.0; extra == 'dev'
Requires-Dist: pytest>=8.4.1; extra == 'dev'
Requires-Dist: respx>=0.20.0; extra == 'dev'
Provides-Extra: docs
Requires-Dist: mkdocs-material>=9.0.0; extra == 'docs'
Requires-Dist: mkdocs>=1.5.0; extra == 'docs'
Requires-Dist: mkdocstrings[python]>=0.20.0; extra == 'docs'
Provides-Extra: server
Requires-Dist: fastapi>=0.68.0; extra == 'server'
Requires-Dist: flask>=2.0.0; extra == 'server'
Requires-Dist: uvicorn>=0.15.0; extra == 'server'
